topsis_raj_102217077/__init__.py
topsis_raj_102217077/topsis.py
topsis_raj_102217077-0.1.1.dist-info/METADATA
topsis_raj_102217077-0.1.1.dist-info/WHEEL
topsis_raj_102217077-0.1.1.dist-info/licenses/LICENSE
topsis_raj_102217077-0.1.1.dist-info/RECORD
