Metadata-Version: 2.4
Name: Topsis-Raj-102217077
Version: 0.1.1
Summary: A package to implement TOPSIS method
Author-email: Raj <jagarwadrajmeena@gmail.com>
License-File: LICENSE
